preditor1bit/PreditorVerilog/preditor_table.v
// Preditor --,-,+,++
module pred_table ( clk, line,  din, dout , reset);
input clk;
input [6:0] line;
input [1:0] din;
output [1:0] dout;
input reset;


reg [1:0] memory[0:127];


always @(posedge clk )
  begin
      memory[line] <= din; 
  end

assign dout = memory[line];


always @( posedge reset) 
			if(reset) // inicia  para testes
				begin
				  memory[0] <= 2'h3;
				  memory[1] <= 2'h2;
				  memory[2] <= 2'h1;
				  memory[3] <= 2'h0;
				end


endmodule

preditor1bit/PreditorVerilog/fsm_pred.v
module fsm_table_cc( din, dout,p );
input [1:0] din;
output [1:0] dout;
input p;

reg [1:0] dout;

parameter MM = 2'b00, M = 2'b01,P = 2'b10,PP = 2'b11;

always @ (*)
begin
  case(din)
    MM: if (p) dout = M; else dout = MM;
    M: if (p) dout = P; else dout = MM;
    P: if (p) dout = PP; else dout = M;
    PP: if (p) dout = PP; else dout = P;
  endcase
end

endmodule

preditor1bit/PreditorVerilog/preditor_tb.v
// iverilog -o my_design fsm_pred.v preditor_table.v preditor_tb.v
/*pred_table ( clk, line,  din, dout , reset);
Then run it:

vvp my_design

Then look at the test.vcd waveform:

gtkwave test.vcd & 
*/
module test;

  /* Make a reset that pulses once. */
  reg reset = 0;
  reg [6:0] address = 7'h0;
  reg p = 0;

  initial begin
     $dumpfile("test.vcd");
    $dumpvars(0,test);
     # 2 reset = 1;
     # 2 reset = 0;
     # 2 address = 6'h2;
     # 10 p = 1;
     # 10 address = 6'h2;
     # 10 p = 0;
     # 10 p = 1;
     # 10 $finish;
  end

  /* Make a regular pulsing clock. */
  reg clk = 0;
  always #1 clk = !clk;

  wire [1:0] dout;
  wire [1:0] din;

fsm_table_cc  CC( .din(dout), .dout(din),.p(p) );
pred_table tab( .clk(clk), .line(address),  .din(din), .dout(dout) , .reset(reset));

  initial
     $monitor("At time %t, address = %0d  dout = %0d",
              $time, address, dout);
endmodule // test

preditor1bit/PreditorVerilog/test.vcd
$date
	Thu Apr 19 12:57:31 2018
$end
$version
	Icarus Verilog
$end
$timescale
	1s
$end
$scope module test $end
$var wire 2 ! din [1:0] $end
$var wire 2 " dout [1:0] $end
$var reg 7 # address [6:0] $end
$var reg 1 $ clk $end
$var reg 1 % p $end
$var reg 1 & reset $end
$scope module CC $end
$var wire 2 ' din [1:0] $end
$var wire 1 ( p $end
$var reg 2 ) dout [1:0] $end
$upscope $end
$scope module tab $end
$var wire 1 * clk $end
$var wire 2 + din [1:0] $end
$var wire 2 , dout [1:0] $end
$var wire 7 - line [6:0] $end
$var wire 1 . reset $end
$upscope $end
$upscope $end
$enddefinitions $end
#0
$dumpvars
0.
b0 -
bx ,
bx +
0*
bx )
0(
bx '
0&
0%
0$
b0 #
bx "
bx !
$end
#1
1$
1*
#2
b10 )
b10 !
b10 +
b11 "
b11 '
b11 ,
0$
0*
1&
1.
#3
b1 )
b1 !
b1 +
b10 "
b10 '
b10 ,
1$
1*
#4
0$
0*
0&
0.
#5
b0 )
b0 !
b0 +
b1 "
b1 '
b1 ,
1$
1*
#6
0$
0*
b10 #
b10 -
#7
b0 "
b0 '
b0 ,
1$
1*
#8
0$
0*
#9
1$
1*
#10
0$
0*
#11
1$
1*
#12
0$
0*
#13
1$
1*
#14
0$
0*
#15
1$
1*
#16
b1 )
b1 !
b1 +
0$
0*
1%
1(
#17
b10 )
b10 !
b10 +
b1 "
b1 '
b1 ,
1$
1*
#18
0$
0*
#19
b11 )
b11 !
b11 +
b10 "
b10 '
b10 ,
1$
1*
#20
0$
0*
#21
b11 "
b11 '
b11 ,
1$
1*
#22
0$
0*
#23
1$
1*
#24
0$
0*
#25
1$
1*
#26
0$
0*
#27
1$
1*
#28
0$
0*
#29
1$
1*
#30
0$
0*
#31
1$
1*
#32
0$
0*
#33
1$
1*
#34
0$
0*
#35
1$
1*
#36
b10 )
b10 !
b10 +
0$
0*
0%
0(
#37
b1 )
b1 !
b1 +
b10 "
b10 '
b10 ,
1$
1*
#38
0$
0*
#39
b0 )
b0 !
b0 +
b1 "
b1 '
b1 ,
1$
1*
#40
0$
0*
#41
b0 "
b0 '
b0 ,
1$
1*
#42
0$
0*
#43
1$
1*
#44
0$
0*
#45
1$
1*
#46
b1 )
b1 !
b1 +
0$
0*
1%
1(
#47
b10 )
b10 !
b10 +
b1 "
b1 '
b1 ,
1$
1*
#48
0$
0*
#49
b11 )
b11 !
b11 +
b10 "
b10 '
b10 ,
1$
1*
#50
0$
0*
#51
b11 "
b11 '
b11 ,
1$
1*
